fcaz/__init__.py
fcaz/constants.py
fcaz-0.0.0.dist-info/LICENSE
fcaz-0.0.0.dist-info/METADATA
fcaz-0.0.0.dist-info/WHEEL
fcaz-0.0.0.dist-info/top_level.txt
fcaz-0.0.0.dist-info/RECORD
