Metadata-Version: 2.1
Name: fcaz
Version: 0.0.0
Summary: Property and Casualty Actuarial Modeling
Home-page: https://github.com/genedan/fcaz
Author: Gene Dan
Author-email: genedan@gmail.com
Project-URL: Documentation, https://genedan.com/fcaz/docs
Classifier: Programming Language :: Python :: 3.10
Classifier: License :: OSI Approved :: Mozilla Public License 2.0 (MPL 2.0)
Classifier: Operating System :: POSIX :: Linux
Requires-Python: >=3.10.0
License-File: LICENSE
Requires-Dist: scipy
